rax_default_network_flags_python_novaclient_ext/__init__.py
rax_default_network_flags_python_novaclient_ext-0.3.2.dist-info/DESCRIPTION.rst
rax_default_network_flags_python_novaclient_ext-0.3.2.dist-info/METADATA
rax_default_network_flags_python_novaclient_ext-0.3.2.dist-info/metadata.json
rax_default_network_flags_python_novaclient_ext-0.3.2.dist-info/RECORD
rax_default_network_flags_python_novaclient_ext-0.3.2.dist-info/top_level.txt
rax_default_network_flags_python_novaclient_ext-0.3.2.dist-info/WHEEL
