Metadata-Version: 2.0
Name: rax-default-network-flags-python-novaclient-ext
Version: 0.3.2
Summary: Novaclient Extension for Instance Default Network Flags
Home-page: https://github.com/rackerlabs/rax_default_network_flags_python_novaclient_ext
Author: Trey Morris
Author-email: trey.morris@rackspace.com
License: Apache License, Version 2.0
Platform: UNKNOWN
Classifier: Development Status :: 5 - Production/Stable
Classifier: Intended Audience :: Developers
Classifier: Intended Audience :: Information Technology
Classifier: License :: OSI Approved :: Apache Software License
Classifier: Operating System :: OS Independent
Classifier: Programming Language :: Python
Requires-Dist: python-novaclient
